arkive/__init__.py
arkive/__main__.py
arkive/actions/__init__.py
arkive/actions/flat.py
arkive/actions/nest.py
arkive/actions/show.py
arkive/console/__init__.py
arkive/console/action.py
arkive/console/parser.py
arkive/core/__init__.py
arkive/core/drive.py
arkive/core/message.py
arkive/core/request.py
arkive/drives/__init__.py
arkive/drives/local/__init__.py
arkive/drives/local/utils.py
arkive/drives/pcloud/__init__.py
arkive/drives/pcloud/utils.py
arkive/utility/__init__.py
arkive/utility/sanitize.py
arkive/utility/table.py
arkive-0.3.1.dist-info/entry_points.txt
arkive-0.3.1.dist-info/LICENSE
arkive-0.3.1.dist-info/WHEEL
arkive-0.3.1.dist-info/METADATA
arkive-0.3.1.dist-info/RECORD
