Metadata-Version: 2.1
Name: arkive
Version: 0.3.1
Summary: Manage your music/audio collections.
Home-page: https://github.com/oroschz/arkive
License: MIT
Author: Orlando Ospino Sánchez
Author-email: oroschz@outlook.com
Requires-Python: >=3.7,<4.0
Classifier: License :: OSI Approved :: MIT License
Classifier: Programming Language :: Python :: 3
Classifier: Programming Language :: Python :: 3.10
Classifier: Programming Language :: Python :: 3.7
Classifier: Programming Language :: Python :: 3.8
Classifier: Programming Language :: Python :: 3.9
Requires-Dist: beautifultable (>=1.0.1,<2.0.0)
Requires-Dist: pathvalidate (>=2.5.0,<3.0.0)
Requires-Dist: tinytag (>=1.8.1,<2.0.0)
Requires-Dist: wcwidth (>=0.2.5,<0.3.0)
Project-URL: Repository, https://github.com/oroschz/arkive
